cellplots/__init__.py
cellplots/_tools/__init__.py
cellplots/_tools/_clean_umap.py
cellplots/core/__init__.py
cellplots/core/_ax_labels.py
cellplots/core/_base_figure_container.py
cellplots/core/_figure_generator.py
cellplots/core/_plot_dimensions.py
cellplots/core/_spine_modifiers.py
cellplots-0.0.0.dist-info/LICENSE
cellplots-0.0.0.dist-info/METADATA
cellplots-0.0.0.dist-info/WHEEL
cellplots-0.0.0.dist-info/top_level.txt
cellplots-0.0.0.dist-info/RECORD
