Metadata-Version: 2.1
Name: cellplots
Version: 0.0.0
Summary: Cell & Genomics Plotting
Home-page: https://github.com/mvinyard/cellplots
Author: Michael E. Vinyard
Author-email: mvinyard@broadinstitute.org
License: MIT
Classifier: Development Status :: 2 - Pre-Alpha
Classifier: Programming Language :: Python :: 3.9
Classifier: Intended Audience :: Science/Research
Classifier: Topic :: Scientific/Engineering :: Bio-Informatics
Requires-Python: >3.9.0
License-File: LICENSE
Requires-Dist: matplotlib >=3.7.2
Requires-Dist: pandas >=2.0.3
Requires-Dist: ABCParse >=0.0.6
